PyCookieCloud/PyCookieCloud.py
PyCookieCloud/PyCryptoJS.py
PyCookieCloud/__init__.py
PyCookieCloud-1.0.4.dist-info/LICENSE
PyCookieCloud-1.0.4.dist-info/METADATA
PyCookieCloud-1.0.4.dist-info/WHEEL
PyCookieCloud-1.0.4.dist-info/top_level.txt
PyCookieCloud-1.0.4.dist-info/RECORD
